lambda_uploader/__init__.py
lambda_uploader/config.py
lambda_uploader/package.py
lambda_uploader/shell.py
lambda_uploader/subscribers.py
lambda_uploader/uploader.py
lambda_uploader/utils.py
lambda_uploader-1.3.0.dist-info/METADATA
lambda_uploader-1.3.0.dist-info/RECORD
lambda_uploader-1.3.0.dist-info/WHEEL
lambda_uploader-1.3.0.dist-info/entry_points.txt
lambda_uploader-1.3.0.dist-info/top_level.txt
