Metadata-Version: 2.1
Name: lambda-uploader
Version: 1.3.0
Summary: AWS Python Lambda Packager
Home-page: https://github.com/rackerlabs/lambda-uploader
Author: Rackers
Maintainer-email: jim.rosser@rackspace.com
License: Apache 2.0
Keywords: aws lambda
Platform: UNKNOWN
Classifier: Programming Language :: Python :: 2.7
Classifier: Programming Language :: Python :: 3
Classifier: Programming Language :: Python :: 3.4
Classifier: Programming Language :: Python :: 3.5
Provides-Extra: test
Provides-Extra: style
Provides-Extra: lint
Provides-Extra: test-requirements
Requires-Dist: boto3 (>=1.4.2)
Requires-Dist: botocore (>=1.4.85)
Requires-Dist: virtualenv
Provides-Extra: lint
Requires-Dist: flake8 (>=2.5.4); extra == 'lint'
Requires-Dist: pylint (>=1.5.5); extra == 'lint'
Provides-Extra: style
Requires-Dist: flake8 (>=2.5.4); extra == 'style'
Requires-Dist: pylint (>=1.5.5); extra == 'style'
Provides-Extra: test
Requires-Dist: coverage (>=4.0.3); extra == 'test'
Requires-Dist: pytest (>=2.9.1); extra == 'test'
Requires-Dist: moto (>=0.4.23); extra == 'test'
Requires-Dist: mock; extra == 'test'
Requires-Dist: nose; extra == 'test'
Provides-Extra: test-requirements
Requires-Dist: coverage (>=4.0.3); extra == 'test-requirements'
Requires-Dist: pytest (>=2.9.1); extra == 'test-requirements'
Requires-Dist: moto (>=0.4.23); extra == 'test-requirements'
Requires-Dist: mock; extra == 'test-requirements'
Requires-Dist: nose; extra == 'test-requirements'
Requires-Dist: flake8 (>=2.5.4); extra == 'test-requirements'
Requires-Dist: pylint (>=1.5.5); extra == 'test-requirements'
